tf_notify/__init__.py
tf_notify/callbacks/__init__.py
tf_notify/callbacks/base.py
tf_notify/callbacks/email.py
tf_notify/callbacks/slack.py
tf_notify/callbacks/telegram.py
tf_notify-0.3.0.dist-info/LICENSE
tf_notify-0.3.0.dist-info/WHEEL
tf_notify-0.3.0.dist-info/METADATA
tf_notify-0.3.0.dist-info/RECORD
