Metadata-Version: 2.1
Name: tf-notify
Version: 0.3.0
Summary: Want to get notified on the progress of your TensorFlow model training? Enter, a TensorFlow Keras callback to send notifications on the messaging app of your choice.
Home-page: https://pypi.org/project/tf-notify
License: Apache-2.0 license
Keywords: tensorflow,keras,callback,notifications,slack,telegram
Author: Ilias Antonopoulos
Author-email: ilias.antonopoulos@yahoo.gr
Requires-Python: >=3.7,<3.11
Classifier: Development Status :: 4 - Beta
Classifier: Intended Audience :: Developers
Classifier: Intended Audience :: Information Technology
Classifier: Intended Audience :: Science/Research
Classifier: License :: OSI Approved :: Apache Software License
Classifier: License :: Other/Proprietary License
Classifier: Natural Language :: English
Classifier: Operating System :: OS Independent
Classifier: Programming Language :: Python :: 3
Classifier: Programming Language :: Python :: 3 :: Only
Classifier: Programming Language :: Python :: 3.10
Classifier: Programming Language :: Python :: 3.7
Classifier: Programming Language :: Python :: 3.8
Classifier: Programming Language :: Python :: 3.9
Classifier: Topic :: Software Development :: Libraries :: Python Modules
Requires-Dist: notifiers (>=1.3.3,<1.4.0)
Requires-Dist: tensorflow (>=2.7.3,<=2.9.1)
Project-URL: Bug Tracker, https://github.com/ilias-ant/tf-notify/issues
Project-URL: Documentation, https://tf-notify.readthedocs.io
Project-URL: Repository, https://github.com/ilias-ant/tf-notify
